setup.py
rtta/__init__.py
rtta/wrapper.py
rtta_adamdeprince-0.0.1.dist-info/METADATA
rtta_adamdeprince-0.0.1.dist-info/WHEEL
rtta_adamdeprince-0.0.1.dist-info/licenses/LICENSE
rtta_adamdeprince-0.0.1.dist-info/RECORD
