Metadata-Version: 2.1
Name: rtta_adamdeprince
Version: 0.0.1
Summary: Realtime incremental Technical Analysis Library in Python
Project-URL: Homepage, https://github.com/pypa/rtta
Project-URL: Issues, https://github.com/pypa/rtta/issues
Author-email: Adam DePrince <adamdeprince@gmail.com>
License-File: LICENSE
Classifier: License :: OSI Approved :: MIT License
Classifier: Operating System :: OS Independent
Classifier: Programming Language :: Python :: 3
Requires-Python: >=3.8
